{
    "canti": [
        {
            "title": "Noi canteremo gloria a Te",
            "author": "author 1",
            "type": "type 1",
            "listen_link": "link1.html",
            "download_link": "download1.html"
        },
        {
            "title": "Acclamate al Signore",
            "author": "author 2",
            "type": "type 2",
            "listen_link": "link2.html",
            "download_link": "download2.html"
        },
        {
            "title": "I cieli narrano",
            "author": "author 3",
            "type": "type 3",
            "listen_link": "link3.html",
            "download_link": "download3.html"
        },
        {
            "title": "Ti esalto, Dio mio Re",
            "author": "author 4",
            "type": "type 4",
            "listen_link": "link4.html",
            "download_link": "download4.html"
        },
        {
            "title": "Gustate e vedete",
            "author": "author 5",
            "type": "type 5",
            "listen_link": "link5.html",
            "download_link": "download5.html"
        },
        {
            "title": "Dove la carità è vera",
            "author": "author 6",
            "type": "type 6",
            "listen_link": "link6.html",
            "download_link": "download6.html"
        },
        {
            "title": "Benedici il Signore",
            "author": "author 7",
            "type": "type 7",
            "listen_link": "link7.html",
            "download_link": "download7.html"
        },
        {
            "title": "Alleluia cantico all'Agnello",
            "author": "author 8",
            "type": "type 8",
            "listen_link": "link8.html",
            "download_link": "download8.html"
        },
        {
            "title": "Alleluia ed oggi ancora",
            "author": "author 9",
            "type": "type 9",
            "listen_link": "link9.html",
            "download_link": "download9.html"
        },
        {
            "title": "Ecco Signore",
            "author": "author 10",
            "type": "type 10",
            "listen_link": "link10.html",
            "download_link": "download10.html"
        },
        {
            "title": "Alleluia, Tu sei Pietro",
            "author": "author 11",
            "type": "type 11",
            "listen_link": "link11.html",
            "download_link": "download11.html"
        },
        {
            "title": "Resta qui con noi",
            "author": "author 12",
            "type": "type 12",
            "listen_link": "link12.html",
            "download_link": "download12.html"
        },
        {
            "title": "Non di solo pane",
            "author": "author 13",
            "type": "type 13",
            "listen_link": "link13.html",
            "download_link": "download13.html"
        },
        {
            "title": "Miserere",
            "author": "author 14",
            "type": "type 14",
            "listen_link": "link14.html",
            "download_link": "download14.html"
        },
        {
            "title": "Chi mi seguirà",
            "author": "author 15",
            "type": "type 15",
            "listen_link": "link15.html",
            "download_link": "download15.html"
        },
        {
            "title": "O Signore nostro Dio",
            "author": "author 16",
            "type": "type 16",
            "listen_link": "link16.html",
            "download_link": "download16.html"
        },
        {
            "title": "Chi ci separerà",
            "author": "author 17",
            "type": "type 17",
            "listen_link": "link17.html",
            "download_link": "download17.html"
        },
        {
            "title": "Alto e glorioso Dio",
            "author": "author 18",
            "type": "type 18",
            "listen_link": "link18.html",
            "download_link": "download18.html"
        },
        {
            "title": "Lodi all'Altissimo",
            "author": "author 19",
            "type": "type 19",
            "listen_link": "link19.html",
            "download_link": "download19.html"
        },
        {
            "title": "Pane di Vita nuova",
            "author": "author 20",
            "type": "type 20",
            "listen_link": "link20.html",
            "download_link": "download20.html"
        },
        {
            "title": "Ecco l'acqua",
            "author": "author 21",
            "type": "type 21",
            "listen_link": "link21.html",
            "download_link": "download21.html"
        },
        {
            "title": "Cantate al Signore",
            "author": "author 22",
            "type": "type 22",
            "listen_link": "link22.html",
            "download_link": "download22.html"
        },
        {
            "title": "Eccomi",
            "author": "author 23",
            "type": "type 23",
            "listen_link": "link23.html",
            "download_link": "download23.html"
        },
        {
            "title": "La vera gioia",
            "author": "author 24",
            "type": "type 24",
            "listen_link": "link24.html",
            "download_link": "download24.html"
        },
        {
            "title": "Benedetto sei Tu Signore",
            "author": "author 25",
            "type": "type 25",
            "listen_link": "link25.html",
            "download_link": "download25.html"
        },
        {
            "title": "Ti rendo grazie",
            "author": "author 26",
            "type": "type 26",
            "listen_link": "link26.html",
            "download_link": "download26.html"
        },
        {
            "title": "Madre fiducia nostra",
            "author": "author 27",
            "type": "type 27",
            "listen_link": "link27.html",
            "download_link": "download27.html"
        },
        {
            "title": "Se m'accogli",
            "author": "author 28",
            "type": "type 28",
            "listen_link": "link28.html",
            "download_link": "download28.html"
        },
        {
            "title": "Santa Maria del cammino",
            "author": "author 29",
            "type": "type 29",
            "listen_link": "link29.html",
            "download_link": "download29.html"
        },
        {
            "title": "Giovanni",
            "author": "author 30",
            "type": "type 30",
            "listen_link": "link30.html",
            "download_link": "download30.html"
        },
        {
            "title": "Alleluia gregoriano",
            "author": "author 31",
            "type": "type 31",
            "listen_link": "link31.html",
            "download_link": "download31.html"
        },
        {
            "title": "Riuniti nel nome del Signore",
            "author": "author 32",
            "type": "type 32",
            "listen_link": "link32.html",
            "download_link": "download32.html"
        },
        {
            "title": "Alleluia Io sono il pane vivo",
            "author": "author 33",
            "type": "type 33",
            "listen_link": "link33.html",
            "download_link": "download33.html"
        },
        {
            "title": "Magnificat - Dio si è fatto come noi",
            "author": "author 34",
            "type": "type 34",
            "listen_link": "link34.html",
            "download_link": "download34.html"
        },
        {
            "title": "Noi veniamo a te",
            "author": "author 35",
            "type": "type 35",
            "listen_link": "link35.html",
            "download_link": "download35.html"
        },
        {
            "title": "Tu sarai profeta",
            "author": "author 36",
            "type": "type 36",
            "listen_link": "link36.html",
            "download_link": "download36.html"
        },
        {
            "title": "La vera Vite",
            "author": "author 37",
            "type": "type 37",
            "listen_link": "link37.html",
            "download_link": "download37.html"
        },
        {
            "title": "Io sarò con Te",
            "author": "author 38",
            "type": "type 38",
            "listen_link": "link38.html",
            "download_link": "download38.html"
        },
        {
            "title": "E' l'ora che pia",
            "author": "author 39",
            "type": "type 39",
            "listen_link": "link39.html",
            "download_link": "download39.html"
        },
        {
            "title": "Lodate Dio",
            "author": "author 40",
            "type": "type 40",
            "listen_link": "link40.html",
            "download_link": "download40.html"
        },
        {
            "title": "Lo spirito del Signore",
            "author": "author 41",
            "type": "type 41",
            "listen_link": "link41.html",
            "download_link": "download41.html"
        },
        {
            "title": "Il tuo popolo in cammino",
            "author": "author 42",
            "type": "type 42",
            "listen_link": "link42.html",
            "download_link": "download42.html"
        },
        {
            "title": "Accogli i nostri doni",
            "author": "author 43",
            "type": "type 43",
            "listen_link": "link43.html",
            "download_link": "download43.html"
        },
        {
            "title": "Lampada per i miei passi",
            "author": "author 44",
            "type": "type 44",
            "listen_link": "link44.html",
            "download_link": "download44.html"
        },
        {
            "title": "O Sion loda il Salvatore",
            "author": "author 45",
            "type": "type 45",
            "listen_link": "link45.html",
            "download_link": "download45.html"
        },
        {
            "title": "E' asceso alla gloria",
            "author": "author 46",
            "type": "type 46",
            "listen_link": "link46.html",
            "download_link": "download46.html"
        },
        {
            "title": "Questo è il mio comandamento",
            "author": "author 47",
            "type": "type 47",
            "listen_link": "link47.html",
            "download_link": "download47.html"
        },
        {
            "title": "Cristo nostra Pasqua",
            "author": "author 48",
            "type": "type 48",
            "listen_link": "link48.html",
            "download_link": "download48.html"
        },
        {
            "title": "La mia Pasqua è il Signore",
            "author": "author 49",
            "type": "type 49",
            "listen_link": "link49.html",
            "download_link": "download49.html"
        },
        {
            "title": "Hosanna",
            "author": "author 50",
            "type": "type 50",
            "listen_link": "link50.html",
            "download_link": "download50.html"
        },
        {
            "title": "O Dio, Tu sei il mio Dio",
            "author": "author 51",
            "type": "type 51",
            "listen_link": "link51.html",
            "download_link": "download51.html"
        },
        {
            "title": "I miei occhi",
            "author": "author 52",
            "type": "type 52",
            "listen_link": "link52.html",
            "download_link": "download52.html"
        },
        {
            "title": "M'invocherà e io lo esaudirò",
            "author": "author 53",
            "type": "type 53",
            "listen_link": "link53.html",
            "download_link": "download53.html"
        },
        {
            "title": "Ti seguirò",
            "author": "author 54",
            "type": "type 54",
            "listen_link": "link54.html",
            "download_link": "download54.html"
        },
        {
            "title": "Tu scendi dalle stelle",
            "author": "author 55",
            "type": "type 55",
            "listen_link": "link55.html",
            "download_link": "download55.html"
        },
        {
            "title": "Adeste Fideles",
            "author": "author 56",
            "type": "type 56",
            "listen_link": "link56.html",
            "download_link": "download56.html"
        },
        {
            "title": "Vieni Signore",
            "author": "author 57",
            "type": "type 57",
            "listen_link": "link57.html",
            "download_link": "download57.html"
        },
        {
            "title": "Camminiamo incontro al Signore",
            "author": "author 58",
            "type": "type 58",
            "listen_link": "link58.html",
            "download_link": "download58.html"
        },
        {
            "title": "Maria porta dell'Avvento",
            "author": "author 59",
            "type": "type 59",
            "listen_link": "link59.html",
            "download_link": "download59.html"
        },
        {
            "title": "Re di Gloria",
            "author": "author 60",
            "type": "type 60",
            "listen_link": "link60.html",
            "download_link": "download60.html"
        },
        {
            "title": "Dov'è carita e amore",
            "author": "author 61",
            "type": "type 61",
            "listen_link": "link61.html",
            "download_link": "download61.html"
        },
        {
            "title": "Ave Maris Stella",
            "author": "author 62",
            "type": "type 62",
            "listen_link": "link62.html",
            "download_link": "download62.html"
        },
        {
            "title": "All'agnello che è stato immolato",
            "author": "author 63",
            "type": "type 63",
            "listen_link": "link63.html",
            "download_link": "download63.html"
        },
        {
            "title": "Perché tu sei con me",
            "author": "author 64",
            "type": "type 64",
            "listen_link": "link64.html",
            "download_link": "download64.html"
        },
        {
            "title": "Le mani alzate",
            "author": "author 65",
            "type": "type 65",
            "listen_link": "link65.html",
            "download_link": "download65.html"
        },
        {
            "title": "Accostiamoci tutti all'altar",
            "author": "author 66",
            "type": "type 66",
            "listen_link": "link66.html",
            "download_link": "download66.html"
        },
        {
            "title": "Regina caeli",
            "author": "author 67",
            "type": "type 67",
            "listen_link": "link67.html",
            "download_link": "download67.html"
        },
        {
            "title": "Sei luce splendida",
            "author": "author 68",
            "type": "type 68",
            "listen_link": "link68.html",
            "download_link": "download68.html"
        },
        {
            "title": "Accogli i nostri doni",
            "author": "author 43",
            "type": "type 43",
            "links": {
                "listen": "link43.html",
                "download": "download43.html"
            }
        },
        {
            "title": "Lampada per i miei passi",
            "author": "author 44",
            "type": "type 44",
            "links": {
                "listen": "link44.html",
                "download": "download44.html"
            }
        },
        {
            "title": "O Sion loda il Salvatore",
            "author": "author 45",
            "type": "type 45",
            "links": {
                "listen": "link45.html",
                "download": "download45.html"
            }
        },
        {
            "title": "E' asceso alla gloria",
            "author": "author 46",
            "type": "type 46",
            "links": {
                "listen": "link46.html",
                "download": "download46.html"
            }
        },
        {
            "title": "Questo è il mio comandamento",
            "author": "author 47",
            "type": "type 47",
            "links": {
                "listen": "link47.html",
                "download": "download47.html"
            }
        },
        {
            "title": "Cristo nostra Pasqua",
            "author": "author 48",
            "type": "type 48",
            "links": {
                "listen": "link48.html",
                "download": "download48.html"
            }
        },
        {
            "title": "La mia Pasqua è il Signore",
            "author": "author 49",
            "type": "type 49",
            "links": {
                "listen": "link49.html",
                "download": "download49.html"
            }
        },
        {
            "title": "Hosanna",
            "author": "author 50",
            "type": "type 50",
            "links": {
                "listen": "link50.html",
                "download": "download50.html"
            }
        },
        {
            "title": "O Dio, Tu sei il mio Dio",
            "author": "author 51",
            "type": "type 51",
            "links": {
                "listen": "link51.html",
                "download": "download51.html"
            }
        },
        {
            "title": "I miei occhi",
            "author": "author 52",
            "type": "type 52",
            "links": {
                "listen": "link52.html",
                "download": "download52.html"
            }
        },
        {
            "title": "M'invocherà e io lo esaudirò",
            "author": "author 53",
            "type": "type 53",
            "links": {
                "listen": "link53.html",
                "download": "download53.html"
            }
        },
        {
            "title": "Ti seguirò",
            "author": "author 54",
            "type": "type 54",
            "links": {
                "listen": "link54.html",
                "download": "download54.html"
            }
        },
        {
            "title": "Tu scendi dalle stelle",
            "author": "author 55",
            "type": "type 55",
            "links": {
                "listen": "link55.html",
                "download": "download55.html"
            }
        },
        {
            "title": "Adeste Fideles",
            "author": "author 56",
            "type": "type 56",
            "links": {
                "listen": "link56.html",
                "download": "download56.html"
            }
        },
        {
            "title": "Vieni Signore",
            "author": "author 57",
            "type": "type 57",
            "links": {
                "listen": "link57.html",
                "download": "download57.html"
            }
        },
        {
            "title": "Camminiamo incontro al Signore",
            "author": "author 58",
            "type": "type 58",
            "links": {
                "listen": "link58.html",
                "download": "download58.html"
            }
        },
        {
            "title": "Maria porta dell'Avvento",
            "author": "author 59",
            "type": "type 59",
            "links": {
                "listen": "link59.html",
                "download": "download59.html"
            }
        },
        {
            "title": "Re di Gloria",
            "author": "author 60",
            "type": "type 60",
            "links": {
                "listen": "link60.html",
                "download": "download60.html"
            }
        },
        {
            "title": "Dov'è carita e amore",
            "author": "author 61",
            "type": "type 61",
            "links": {
                "listen": "link61.html",
                "download": "download61.html"
            }
        },
        {
            "title": "Ave Maris Stella",
            "author": "author 62",
            "type": "type 62",
            "links": {
                "listen": "link62.html",
                "download": "download62.html"
            }
        },
        {
            "title": "All'agnello che è stato immolato",
            "author": "author 63",
            "type": "type 63",
            "links": {
                "listen": "link63.html",
                "download": "download63.html"
            }
        },
        {
            "title": "Perché tu sei con me",
            "author": "author 64",
            "type": "type 64",
            "links": {
                "listen": "link64.html",
                "download": "download64.html"
            }
        },
        {
            "title": "Le mani alzate",
            "author": "author 65",
            "type": "type 65",
            "links": {
                "listen": "link65.html",
                "download": "download65.html"
            }
        },
        {
            "title": "Accostiamoci tutti all'altar",
            "author": "author 66",
            "type": "type 66",
            "links": {
                "listen": "link66.html",
                "download": "download66.html"
            }
        },
        {
            "title": "Regina caeli",
            "author": "author 67",
            "type": "type 67",
            "links": {
                "listen": "link67.html",
                "download": "download67.html"
            }
        },
        {
            "title": "Sei luce splendida",
            "author": "author 68",
            "type": "type 68",
            "links": {
                "listen": "link68.html",
                "download": "download68.html"
            }
        },
        {
            "title": "Alleluia",
            "author": "author 69",
            "type": "type 69",
            "links": {
                "listen": "link69.html",
                "download": "download69.html"
            }
        },
        {
            "title": "Tu quando verrai",
            "author": "author 70",
            "type": "type 70",
            "links": {
                "listen": "link70.html",
                "download": "download70.html"
            }
        },
        {
            "title": "Astro del ciel",
            "author": "author 71",
            "type": "type 71",
            "links": {
                "listen": "link71.html",
                "download": "download71.html"
            }
        },
        {
            "title": "Andrò a vederla un dì",
            "author": "author 72",
            "type": "type 72",
            "links": {
                "listen": "link72.html",
                "download": "download72.html"
            }
        },
        {
            "title": "Inni e canti",
            "author": "author 73",
            "type": "type 73",
            "links": {
                "listen": "link73.html",
                "download": "download73.html"
            }
        },
        {
            "title": "Fratello sole, sorella luna",
            "author": "author 74",
            "type": "type 74",
            "links": {
                "listen": "link74.html",
                "download": "download74.html"
            }
        },
        {
            "title": "Il Signore è la mia salvezza",
            "author": "author 75",
            "type": "type 75",
            "links": {
                "listen": "link75.html",
                "download": "download75.html"
            }
        },
        {
            "title": "Dell'aurora Tu sorgi più bella",
            "author": "author 76",
            "type": "type 76",
            "links": {
                "listen": "link76.html",
                "download": "download76.html"
            }
        },
        {
            "title": "T'adoriam, Ostia divina",
            "author": "author 77",
            "type": "type 77",
            "links": {
                "listen": "link77.html",
                "download": "download77.html"
            }
        },
        {
            "title": "Mira il tuo popolo",
            "author": "author 78",
            "type": "type 78",
            "links": {
                "listen": "link78.html",
                "download": "download78.html"
            }
        },
        {
            "title": "Il signore è vicino",
            "author": "author 79",
            "type": "type 79",
            "links": {
                "listen": "link79.html",
                "download": "download79.html"
            }
        },
        {
            "title": "Cielo nuovo",
            "author": "author 80",
            "type": "type 80",
            "links": {
                "listen": "link80.html",
                "download": "download80.html"
            }
        },
        {
            "title": "Frutto della nostra terra",
            "author": "author 81",
            "type": "type 81",
            "links": {
                "listen": "link81.html",
                "download": "download81.html"
            }
        },
        {
            "title": "Nel sole dell'aurora",
            "author": "author 82",
            "type": "type 82",
            "links": {
                "listen": "link82.html",
                "download": "download82.html"
            }
        },
        {
            "title": "Ti ringrazio, o mio Signore",
            "author": "author 83",
            "type": "type 83",
            "links": {
                "listen": "link83.html",
                "download": "download83.html"
            }
        },
        {
            "title": "Inno d'Amore",
            "author": "author 84",
            "type": "type 84",
            "links": {
                "listen": "link84.html",
                "download": "download84.html"
            }
        },
        {
            "title": "Vi darò un cuore nuovo",
            "author": "author 85",
            "type": "type 85",
            "links": {
                "listen": "link85.html",
                "download": "download85.html"
            }
        },
        {
            "title": "Beati quelli che listen_linkno",
            "author": "author 86",
            "type": "type 86",
            "links": {
                "listen": "link86.html",
                "download": "download86.html"
            }
        },
        {
            "title": "Vieni ancora, Gesù",
            "author": "author 87",
            "type": "type 87",
            "links": {
                "listen": "link87.html",
                "download": "download87.html"
            }
        },
        {
            "title": "Symbolum 77",
            "author": "author 88",
            "type": "type 88",
            "links": {
                "listen": "link88.html",
                "download": "download88.html"
            }
        },
        {
            "title": "Dio si è fatto come noi",
            "author": "author 89",
            "type": "type 89",
            "links": {
                "listen": "link89.html",
                "download": "download89.html"
            }
        },
        {
            "title": "Ecco quel che abbiamo",
            "author": "author 90",
            "type": "type 90",
            "links": {
                "listen": "link90.html",
                "download": "download90.html"
            }
        },
        {
            "title": "Credo in te Signore",
            "author": "author 91",
            "type": "type 91",
            "links": {
                "listen": "link91.html",
                "download": "download91.html"
            }
        },
        {
            "title": "Pane del Cielo",
            "author": "author 92",
            "type": "type 92",
            "links": {
                "listen": "link92.html",
                "download": "download92.html"
            }
        },
        {
            "title": "Salve Regina",
            "author": "author 93",
            "type": "type 93",
            "links": {
                "listen": "link93.html",
                "download": "download93.html"
            }
        },
        {
            "title": "E' bello lodarti",
            "author": "author 94",
            "type": "type 94",
            "links": {
                "listen": "link94.html",
                "download": "download94.html"
            }
        },
        {
            "title": "O cieli piovete dall'alto",
            "author": "author 95",
            "type": "type 95",
            "links": {
                "listen": "link95.html",
                "download": "download95.html"
            }
        },
        {
            "title": "Vieni Spirito d'Amore",
            "author": "author 96",
            "type": "type 96",
            "links": {
                "listen": "link96.html",
                "download": "download96.html"
            }
        },
        {
            "title": "Inni e canti",
            "author": "author 97",
            "type": "type 97",
            "links": {
                "listen": "link97.html",
                "download": "download97.html"
            }
        },
        {
            "title": "Osanna al figlio di David",
            "author": "author 98",
            "type": "type 98",
            "links": {
                "listen": "link98.html",
                "download": "download98.html"
            }
        },
        {
            "title": "Se qualcuno ha dei beni",
            "author": "author 99",
            "type": "type 99",
            "links": {
                "listen": "link99.html",
                "download": "download99.html"
            }
        },
        {
            "title": "In notte placida",
            "author": "author 100",
            "type": "type 100",
            "links": {
                "listen": "link100.html",
                "download": "download100.html"
            }
        },
        {
            "title": "Madre mia bellissima",
            "author": "author 101",
            "type": "type 101",
            "links": {
                "listen": "link101.html",
                "download": "download101.html"
            }
        },
        {
            "title": "Il pane del cammino",
            "author": "author 102",
            "type": "type 102",
            "links": {
                "listen": "link102.html",
                "download": "download102.html"
            }
        },
        {
            "title": "Immacolata vergine bella",
            "author": "author 103",
            "type": "type 103",
            "links": {
                "listen": "link103.html",
                "download": "download103.html"
            }
        },
        {
            "title": "Rallegrati Gerusalemme",
            "author": "author 104",
            "type": "type 104",
            "links": {
                "listen": "link104.html",
                "download": "download104.html"
            }
        },
        {
            "title": "Come tu mi vuoi",
            "author": "author 105",
            "type": "type 105",
            "links": {
                "listen": "link105.html",
                "download": "download105.html"
            }
        },
        {
            "title": "Venite fedeli",
            "author": "author 106",
            "type": "type 106",
            "links": {
                "listen": "link106.html",
                "download": "download106.html"
            }
        },
        {
            "title": "Resta con noi Signore la sera",
            "author": "author 107",
            "type": "type 107",
            "links": {
                "listen": "link107.html",
                "download": "download107.html"
            }
        },
        {
            "title": "Andate per le strade",
            "author": "author 108",
            "type": "type 108",
            "links": {
                "listen": "link108.html",
                "download": "download108.html"
            }
        },
        {
            "title": "Gloria a te",
            "author": "author 109",
            "type": "type 109",
            "links": {
                "listen": "link109.html",
                "download": "download109.html"
            }
        },
        {
            "title": "Davanti al Re",
            "author": "author 110",
            "type": "type 110",
            "links": {
                "listen": "link110.html",
                "download": "download110.html"
            }
        },
        {
            "title": "Te lodiamo Trinità",
            "author": "author 111",
            "type": "type 111",
            "links": {
                "listen": "link111.html",
                "download": "download111.html"
            }
        },
        {
            "title": "Signore, da chi andremo",
            "author": "author 112",
            "type": "type 112",
            "links": {
                "listen": "link112.html",
                "download": "download112.html"
            }
        },
        {
            "title": "Come un fiore",
            "author": "author 113",
            "type": "type 113",
            "links": {
                "listen": "link113.html",
                "download": "download113.html"
            }
        },
        {
            "title": "Ti ringrazio",
            "author": "author 114",
            "type": "type 114",
            "links": {
                "listen": "link114.html",
                "download": "download114.html"
            }
        },
        {
            "title": "Pange lingua",
            "author": "author 115",
            "type": "type 115",
            "links": {
                "listen": "link115.html",
                "download": "download115.html"
            }
        },
        {
            "title": "Alleluia lodate il Signore",
            "author": "author 116",
            "type": "type 116",
            "links": {
                "listen": "link116.html",
                "download": "download116.html"
            }
        },
        {
            "title": "Sei tu Signore il pane",
            "author": "author 117",
            "type": "type 117",
            "links": {
                "listen": "link117.html",
                "download": "download117.html"
            }
        },
        {
            "title": "Guada questa offerta",
            "author": "author 118",
            "type": "type 118",
            "links": {
                "listen": "link118.html",
                "download": "download118.html"
            }
        },
        {
            "title": "Il Signore è il mio Pastore",
            "author": "author 119",
            "type": "type 119",
            "links": {
                "listen": "link119.html",
                "download": "download119.html"
            }
        },
        {
            "title": "Te al centro del mio cuore",
            "author": "author 120",
            "type": "type 120",
            "links": {
                "listen": "link120.html",
                "download": "download120.html"
            }
        }
    ]
}